ip_rotator/__init__.py
ip_rotator/ip_rotator.py
ip_rotator-1.3.dist-info/LICENSE
ip_rotator-1.3.dist-info/METADATA
ip_rotator-1.3.dist-info/WHEEL
ip_rotator-1.3.dist-info/top_level.txt
ip_rotator-1.3.dist-info/RECORD
