Metadata-Version: 2.1
Name: ip-rotator
Version: 1.3
Summary: Rotate IP In Http Request
Author-email: Anish <anishshakthivelnadar@gmail.com>
Project-URL: Homepage, https://github.com/Anish0612/ip_rotator
Project-URL: Bug Tracker, https://github.com/Anish0612/ip_rotator/issues
Classifier: Programming Language :: Python :: 3
Classifier: License :: OSI Approved :: MIT License
Classifier: Operating System :: OS Independent
Requires-Python: >=3.7
License-File: LICENSE
Requires-Dist: requests
Requires-Dist: beautifulsoup4
Requires-Dist: lxml
